Ejercicio2/Ejercicio2.v
module ROM4kx8 (input wire [11:0]Address, output wire [7:0]Data);           
	reg [11:0] ROM [0:4095] ;  
    
	assign Data = ROM[Address];

initial begin
  $readmemb("Lista.txt", ROM); 
end

endmodule

Ejercicio2/Ejercicio2_tb.v
module Ejercicio2_tb();

reg [11:0]Address;
wire [7:0]Data; 

ROM4kx8 R1(Address, Data);

initial 
	begin
		
		#1 $display("");
		$display("Ejercicio 2");
		$display("  Address | Data ");
		$display("--------|------");
		$monitor("%d      | %d ", Address, Data);

		Address = 10;
		#1 Address = 25;
		#1 Address = 50;
		#1 Address = 75;
		#1 Address = 100;
		#1 Address = 33;
		#1 Address = 99;
		#1 Address = 21;
		#1 Address = 73;
		#1 Address = 245;
		

	end
 
initial
#11 $finish; 

initial begin
    $dumpfile("Ejercicio2_tb.vcd");
    $dumpvars(0, Ejercicio2_tb);
end

endmodule

Ejercicio2/Ejercicio2_tb.vcd
$date
	Sun Oct 25 05:15:18 2020
$end
$version
	Icarus Verilog
$end
$timescale
	1ps
$end
$scope module Ejercicio2_tb $end
$var wire 8 ! Data [7:0] $end
$var reg 12 " Address [11:0] $end
$scope module R1 $end
$var wire 12 # Address [11:0] $end
$var wire 8 $ Data [7:0] $end
$upscope $end
$upscope $end
$enddefinitions $end
#0
$dumpvars
bx $
bx #
bx "
bx !
$end
#1
b1010 !
b1010 $
b1010 "
b1010 #
#2
b11001 !
b11001 $
b11001 "
b11001 #
#3
b110010 !
b110010 $
b110010 "
b110010 #
#4
b1001011 !
b1001011 $
b1001011 "
b1001011 #
#5
b1100100 !
b1100100 $
b1100100 "
b1100100 #
#6
b100001 !
b100001 $
b100001 "
b100001 #
#7
b1100011 !
b1100011 $
b1100011 "
b1100011 #
#8
b10101 !
b10101 $
b10101 "
b10101 #
#9
b1001001 !
b1001001 $
b1001001 "
b1001001 #
#10
b11110101 !
b11110101 $
b11110101 "
b11110101 #
