Ejercicio3/Ejercicio3.v
module ALU (input wire [3:0]A, input wire [3:0]B, input wire [2:0]Sel, output reg [3:0]Y); 
reg [4:0]C;
reg Menor;
	always @ (A or B or Sel) 
		case (Sel) 
			0 : Y = A & B; 
			1 : Y = A | B; 
			2 : begin
					C = A + B; 
					Y[0] = C[0];
					Y[1] = C[1];
					Y[2] = C[2];
					Y[3] = C[3];
				end
			3 : Y = 0;
			4 : Y = A & ~B;
			5 : Y = A | ~B;
			6 : begin
					C = A - B; 
					Y[0] = C[0];
					Y[1] = C[1];
					Y[2] = C[2];
					Y[3] = C[3];
				end
			7 : begin
					Menor = (A < B);
					if (Menor)
						begin
						Y = 4'b1111;
						end 
					else 
						begin
						Y = 0;
						end
				end
			default : $display("Error in Sel"); 
		endcase 
    
endmodule

Ejercicio3/Ejercicio3_tb.v
module Ejercicio3_tb();

reg [3:0]A; reg [3:0]B; reg [2:0]sel;
wire [3:0]Y;

ALU A1 (A, B, sel, Y);

initial begin

    #1 $display("\n");
	$display("Ejercicio 3");
    $display(" A     B   Sel  | Y");
    $display("---------------------");
    $monitor("%b %b %b  |%b", A, B, sel, Y);
	
	//Prueba de AND 
	sel = 0; A = 1; B = 1;
	#1 B = 7;
	#1 A = 5;
	#1 B = 15;
	#1 A = 15;
	//Prueba de OR
	#1 sel = 1; A = 0; B = 0;
	#1 A = 15;
	#1 A = 0;
	#1 B = 15;
	#1 A = 15;
	//Prueba de Suma
	#1 sel = 2; A = 0; B = 0;
	#1 A = 1; B = 1;
	#1 A = 6; B = 4;
	#1 A = 1; B = 15;
	#1 A = 14; B = 1;
	//Prueba de Sel=3
	#1 sel = 3; A = 15; B = 15;
	#1 A = 1; B = 1;
	#1 A = 7; B = 5;
	//Prueba de A AND ~B
	#1 sel = 4; A = 0; B = 0;
	#1 A = 15;
	#1 B = 15;
	#1 A = 0;
	#1 A = 8; B = 7;
	//Prueba de A OR ~B
	#1 sel = 5; A = 0; B = 0;
	#1 B = 15;
	#1 A = 15;
	#1 B = 0;
	#1 A = 8; B = 8;
	//Prueban de Resta
	#1 sel = 6; A = 0; B = 0;
	#1 A = 10; B = 3;
	#1 A = 15; B = 11;
	#1 A = 9; B = 9;
	#1 A = 2; B = 1;
	//Prueba Menor Que
	#1 sel = 7; A = 0; B = 0;
	#1 A = 1; B = 1;
	#1 A = 15; B = 15;
	#1 A = 1; B = 15;
	#1 A = 7; B = 11;
	#1 A = 13; B = 10;
	#1 A = 5; B = 1;
	
  end 
  
  initial
#41 $finish; 

initial begin
    $dumpfile("Ejercicio3_tb.vcd");
    $dumpvars(0, Ejercicio3_tb);
end

endmodule

Ejercicio3/Ejercicio3_tb.vcd
$date
	Sun Oct 25 05:31:57 2020
$end
$version
	Icarus Verilog
$end
$timescale
	1ps
$end
$scope module Ejercicio3_tb $end
$var wire 4 ! Y [3:0] $end
$var reg 4 " A [3:0] $end
$var reg 4 # B [3:0] $end
$var reg 3 $ sel [2:0] $end
$scope module A1 $end
$var wire 4 % A [3:0] $end
$var wire 4 & B [3:0] $end
$var wire 3 ' Sel [2:0] $end
$var reg 5 ( C [4:0] $end
$var reg 1 ) Menor $end
$var reg 4 * Y [3:0] $end
$upscope $end
$upscope $end
$enddefinitions $end
#0
$dumpvars
bx *
x)
bx (
bx '
bx &
bx %
bx $
bx #
bx "
bx !
$end
#1
b1 !
b1 *
b1 #
b1 &
b1 "
b1 %
b0 $
b0 '
#2
b111 #
b111 &
#3
b101 !
b101 *
b101 "
b101 %
#4
b1111 #
b1111 &
#5
b1111 !
b1111 *
b1111 "
b1111 %
#6
b0 !
b0 *
b0 #
b0 &
b0 "
b0 %
b1 $
b1 '
#7
b1111 !
b1111 *
b1111 "
b1111 %
#8
b0 !
b0 *
b0 "
b0 %
#9
b1111 !
b1111 *
b1111 #
b1111 &
#10
b1111 "
b1111 %
#11
b0 !
b0 *
b0 (
b0 #
b0 &
b0 "
b0 %
b10 $
b10 '
#12
b10 !
b10 *
b10 (
b1 #
b1 &
b1 "
b1 %
#13
b1010 !
b1010 *
b1010 (
b100 #
b100 &
b110 "
b110 %
#14
b0 !
b0 *
b10000 (
b1111 #
b1111 &
b1 "
b1 %
#15
b1111 !
b1111 *
b1111 (
b1 #
b1 &
b1110 "
b1110 %
#16
b0 !
b0 *
b1111 #
b1111 &
b1111 "
b1111 %
b11 $
b11 '
#17
b1 #
b1 &
b1 "
b1 %
#18
b101 #
b101 &
b111 "
b111 %
#19
b0 #
b0 &
b0 "
b0 %
b100 $
b100 '
#20
b1111 !
b1111 *
b1111 "
b1111 %
#21
b0 !
b0 *
b1111 #
b1111 &
#22
b0 "
b0 %
#23
b1000 !
b1000 *
b111 #
b111 &
b1000 "
b1000 %
#24
b1111 !
b1111 *
b0 #
b0 &
b0 "
b0 %
b101 $
b101 '
#25
b0 !
b0 *
b1111 #
b1111 &
#26
b1111 !
b1111 *
b1111 "
b1111 %
#27
b0 #
b0 &
#28
b1000 #
b1000 &
b1000 "
b1000 %
#29
b0 !
b0 *
b0 (
b0 #
b0 &
b0 "
b0 %
b110 $
b110 '
#30
b111 !
b111 *
b111 (
b11 #
b11 &
b1010 "
b1010 %
#31
b100 !
b100 *
b100 (
b1011 #
b1011 &
b1111 "
b1111 %
#32
b0 !
b0 *
b0 (
b1001 #
b1001 &
b1001 "
b1001 %
#33
b1 !
b1 *
b1 (
b1 #
b1 &
b10 "
b10 %
#34
b0 !
b0 *
0)
b0 #
b0 &
b0 "
b0 %
b111 $
b111 '
#35
b1 #
b1 &
b1 "
b1 %
#36
b1111 #
b1111 &
b1111 "
b1111 %
#37
b1111 !
b1111 *
1)
b1 "
b1 %
#38
b1011 #
b1011 &
b111 "
b111 %
#39
b0 !
b0 *
0)
b1010 #
b1010 &
b1101 "
b1101 %
#40
b1 #
b1 &
b101 "
b101 %
